odbclient/__init__.py
odbclient/odbclient.py
pylife_odbclient-2.1.4.dist-info/licenses/AUTHORS.rst
pylife_odbclient-2.1.4.dist-info/licenses/LICENSE
pylife_odbclient-2.1.4.dist-info/METADATA
pylife_odbclient-2.1.4.dist-info/WHEEL
pylife_odbclient-2.1.4.dist-info/top_level.txt
pylife_odbclient-2.1.4.dist-info/RECORD
