Metadata-Version: 2.4
Name: pylife-odbclient
Version: 2.1.4
Summary: A Python 3 client for odbAccess using pylife-odbserver
Home-page: https://github.com/boschresearch/pylife
Author: Johannes Mueller
Author-email: johannes.mueller4@de.bosch.com
License: Apache-2
Project-URL: Documentation, https://pylife.readthedocs.io
Platform: any
Classifier: Development Status :: 4 - Beta
Classifier: Programming Language :: Python
Requires-Python: >=3
License-File: LICENSE
License-File: AUTHORS.rst
Requires-Dist: importlib-metadata; python_version < "3.8"
Requires-Dist: pandas
Requires-Dist: numpy
Provides-Extra: testing
Requires-Dist: setuptools; extra == "testing"
Requires-Dist: pytest; extra == "testing"
Requires-Dist: pytest-cov; extra == "testing"
Dynamic: license-file
Dynamic: requires-python
